Workbook

Sheet Task
C3: Sr No | D3: Task
C4: 1 | D4: Get the Cross-Sold GWP for Liability products and which is the highest Cross-Sold Product?
C5: 2 | D5: Create a dashboard to analyse POS Data with KPIs and gather insights on the same
C6: 3 | D6: Map policy category to the policy type using data from appendix
C8: Average commission to consider
C9: Product | E9: %
C10: Liability - Non POS | E10: 0.2
C11: P&C - Non POS | E11: 0.2
C12: Others -Non POS | E12: 0.15
C13: Policies booked through POS GTM | E13: 0.05 | F13: -> Retained by BK

Sheet Liability_client

Sheet Cross Sold GWP
A2: Client Id | B2: COUNTA of Policy Name | C2: SUM of Gross Premium
A3: 1 | B3: 4 | C3: 8358500
A4: 4 | B4: 1 | C4: 2714000
A5: 6 | B5: 19 | C5: 17967556
A6: 8 | B6: 2 | C6: 3948062
A7: 10 | B7: 2 | C7: 2047600
A8: 11 | B8: 1 | C8: 908400
A9: 12 | B9: 1 | C9: 8850000
A10: 15 | B10: 67 | C10: 325250630
A11: 16 | B11: 1 | C11: 3717000
A12: 17 | B12: 3 | C12: 1323558
A13: 18 | B13: 3 | C13: 2706980
A14: 20 | B14: 3 | C14: 301562
... A3376: 3619 | B3376: 1 | C3376: 3540000
A3377: (blank)

Sheet Raw Data
A1: PL NO | B1: Client Id | C1: Sales Channel | D1: POS Location | E1: Insurer Name | F1: Category | G1: Policy Name | H1: Policy Start Date | I1: Policy End Date | J1: Gross Premium | K1: Total GST Amount | L1: Net Premium | M1: Total Brokerage Received | N1: Client Type | O1: Policy MIS New | P1: Type of Purchase (New Client/Old Client) | Q1: HasLiability | R1: IsCrossSold
A2: PL 158 | B2: 67 | C2: Ads | D2: Not POS | E2: Future Generali India Insurance Co Ltd | F2: =VLOOKUP(G2,'Policy Type'!$A:$B,2,FALSE) -> Liability | G2: Workmen Compensation | H2: 45139 | I2: 45504 | J2: 6200800 | K2: =J2*0.18 -> 1116144 | L2: =J2+K2 -> 7316944 | M2: =L2*0.2 -> 1463388.8 | N2: Corporate | O2: Rollover | P2: =IF(COUNTIF(B:B,B2)=1,"New Client","Old Client") -> Old Client | Q2: =IF(COUNTIFS($B:$B,$B2,$F:$F,"Liability")>0,"Yes","No") -> Yes | R2: =IF(AND($Q2="Yes",$F2<>"Liability"),"Cross-Sold","")
A3: PL 252 | B3: 70 | C3: BD | D3: Not POS | E3: Bajaj Allianz General Insurance Co Ltd | F3: =VLOOKUP(G3,'Policy Type'!$A:$B,2,FALSE) -> P&C | G3: Burglary | H3: 45139 | I3: 45504 | J3: 550000 | K3: =J3*0.18 -> 99000 | L3: =J3+K3 -> 649000 | M3: =L3*0.2 -> 129800 | N3: Corporate | O3: Rollover | P3: =IF(COUNTIF(B:B,B3)=1,"New Client","Old Client") -> Old Client | Q3: =IF(COUNTIFS($B:$B,$B3,$F:$F,"Liability")>0,"Yes","No") -> Yes | R3: =IF(AND($Q3="Yes",$F3<>"Liability"),"Cross-Sold","") -> Cross-Sold
A4: PL 324 | B4: 122 | C4: POS | D4: Nagpur | E4: Bajaj Allianz General Insurance Co Ltd | F4: =VLOOKUP(G4,'Policy Type'!$A:$B,2,FALSE) -> P&C | G4: Marine Open | H4: 45139 | I4: 45504 | J4: 4130100 | K4: =J4*0.18 -> 743418 | L4: =J4+K4 -> 4873518 | M4: =L4*0.05 -> 243675.9 | N4: Corporate | O4: New | P4: =IF(COUNTIF(B:B,B4)=1,"New Client","Old Client") -> Old Client | Q4: =IF(COUNTIFS($B:$B,$B4,$F:$F,"Liability")>0,"Yes","No") -> Yes | R4: =IF(AND($Q4="Yes",$F4<>"Liability"),"Cross-Sold","") -> Cross-Sold
A5: PL 382 | B5: 146 | C5: BD | D5: Not POS | E5: Bajaj Allianz General Insurance Co Ltd | F5: =VLOOKUP(G5,'Policy Type'!$A:$B,2,FALSE) -> P&C | G5: Premium Personal Guard | H5: 45150 | I5: 45515 | J5: 153400 | K5: =J5*0.18 -> 27612 | L5: =J5+K5 -> 181012 | M5: =L5*0.2 -> 36202.4 | N5: Retail | O5: Renew | P5: =IF(COUNTIF(B:B,B5)=1,"New Client","Old Client") -> New Client | Q5: =IF(COUNTIFS($B:$B,$B5,$F:$F,"Liability")>0,"Yes","No") -> No | R5: =IF(AND($Q5="Yes",$F5<>"Liability"),"Cross-Sold","")
A6: PL 390 | B6: 149 | C6: Ads | D6: Not POS | E6: Bajaj Allianz General Insurance Co Ltd | F6: =VLOOKUP(G6,'Policy Type'!$A:$B,2,FALSE) -> P&C | G6: Two Wheeler | H6: 45139 | I6: 45504 | J6: 141128 | K6: =J6*0.18 -> 25403.04 | L6: =J6+K6 -> 166531.04 | M6: =L6*0.2 -> 33306.208 | N6: Retail | O6: Renew | P6: =IF(COUNTIF(B:B,B6)=1,"New Client","Old Client") -> New Client | Q6: =IF(COUNTIFS($B:$B,$B6,$F:$F,"Liability")>0,"Yes","No") -> No | R6: =IF(AND($Q6="Yes",$F6<>"Liability"),"Cross-Sold","")
A7: PL 404 | B7: 153 | C7: Offline | D7: Not POS | E7: Bajaj Allianz General Insurance Co Ltd | F7: =VLOOKUP(G7,'Policy Type'!$A:$B,2,FALSE) -> Liability | G7: D & O | H7: 45139 | I7: 45504 | J7: 2124000 | K7: =J7*0.18 -> 382320 | L7: =J7+K7 -> 2506320 | M7: =L7*0.2 -> 501264 | N7: Corporate | O7: Renew | P7: =IF(COUNTIF(B:B,B7)=1,"New Client","Old Client") -> New Client | Q7: =IF(COUNTIFS($B:$B,$B7,$F:$F,"Liability")>0,"Yes","No") -> Yes | R7: =IF(AND($Q7="Yes",$F7<>"Liability"),"Cross-Sold","")
A8: PL 437 | B8: 165 | C8: Offline | D8: Not POS | E8: United India Insurance Co Ltd | F8: =VLOOKUP(G8,'Policy Type'!$A:$B,2,FALSE) -> P&C | G8: Two Wheeler | H8: 45139 | I8: 45504 | J8: 286740 | K8: =J8*0.18 -> 51613.2 | L8: =J8+K8 -> 338353.2 | M8: =L8*0.2 -> 67670.64 | N8: Retail | O8: Renew | P8: =IF(COUNTIF(B:B,B8)=1,"New Client","Old Client") -> Old Client | Q8: =IF(COUNTIFS($B:$B,$B8,$F:$F,"Liability")>0,"Yes","No") -> Yes | R8: =IF(AND($Q8="Yes",$F8<>"Liability"),"Cross-Sold","") -> Cross-Sold
A9: PL 449 | B9: 171 | C9: Ads | D9: Not POS | E9: United India Insurance Co Ltd | F9: =VLOOKUP(G9,'Policy Type'!$A:$B,2,FALSE) -> P&C | G9: Two wheeler - TP | H9: 45143 | I9: 45508 | J9: 116700 | K9: =J9*0.18 -> 21006 | L9: =J9+K9 -> 137706 | M9: =L9*0.2 -> 27541.2 | N9: Retail | O9: Rollover | P9: =IF(COUNTIF(B:B,B9)=1,"New Client","Old Client") -> New Client | Q9: =IF(COUNTIFS($B:$B,$B9,$F:$F,"Liability")>0,"Yes","No") -> No | R9: =IF(AND($Q9="Yes",$F9<>"Liability"),"Cross-Sold","")
A10: PL 481 | B10: 182 | C10: Offline | D10: Not POS | E10: Future Generali India Insurance Co Ltd | F10: =VLOOKUP(G10,'Policy Type'!$A:$B,2,FALSE) -> P&C | G10: Two Wheeler | H10: 45139 | I10: 45504 | J10: 118472 | K10: =J10*0.18 -> 21324.96 | L10: =J10+K10 -> 139796.96 | M10: =L10*0.2 -> 27959.392 | N10: Corporate | O10: Renew | P10: =IF(COUNTIF(B:B,B10)=1,"New Client","Old Client") -> Old Client | Q10: =IF(COUNTIFS($B:$B,$B10,$F:$F,"Liability")>0,"Yes","No") -> No | R10: =IF(AND($Q10="Yes",$F10<>"Liability"),"Cross-Sold","")
A11: PL 511 | B11: 170 | C11: Ads | D11: Not POS | E11: Bajaj Allianz General Insurance Co Ltd | F11: =VLOOKUP(G11,'Policy Type'!$A:$B,2,FALSE) -> P&C | G11: Two Wheeler | H11: 45161 | I11: 45526 | J11: 148798 | K11: =J11*0.18 -> 26783.64 | L11: =J11+K11 -> 175581.64 | M11: =L11*0.2 -> 35116.328 | N11: Retail | O11: Renew | P11: =IF(COUNTIF(B:B,B11)=1,"New Client","Old Client") -> Old Client | Q11: =IF(COUNTIFS($B:$B,$B11,$F:$F,"Liability")>0,"Yes","No") -> Yes | R11: =IF(AND($Q11="Yes",$F11<>"Liability"),"Cross-Sold","") -> Cross-Sold
A12: PL 513 | B12: 188 | C12: POS | D12: Ahemdabad | E12: Bajaj Allianz General Insurance Co Ltd | F12: =VLOOKUP(G12,'Policy Type'!$A:$B,2,FALSE) -> P&C | G12: Two Wheeler | H12: 45142 | I12: 45507 | J12: 141954 | K12: =J12*0.18 -> 25551.72 | L12: =J12+K12 -> 167505.72 | M12: =L12*0.05 -> 8375.286 | N12: Retail | O12: Renew | P12: =IF(COUNTIF(B:B,B12)=1,"New Client","Old Client") -> Old Client | Q12: =IF(COUNTIFS($B:$B,$B12,$F:$F,"Liability")>0,"Yes","No") -> Yes | R12: =IF(AND($Q12="Yes",$F12<>"Liability"),"Cross-Sold","") -> Cross-Sold
A13: PL 515 | B13: 189 | C13: POS | D13: Ahemdabad | E13: Bajaj Allianz General Insurance Co Ltd | F13: =VLOOKUP(G13,'Policy Type'!$A:$B,2,FALSE) -> P&C | G13: Private Car | H13: 45140 | I13: 45505 | J13: 651800 | K13: =J13*0.18 -> 117324 | L13: =J13+K13 -> 769124 | M13: =L13*0.05 -> 38456.2 | N13: Corporate | O13: Renew | P13: =IF(COUNTIF(B:B,B13)=1,"New Client","Old Client") -> Old Client | Q13: =IF(COUNTIFS($B:$B,$B13,$F:$F,"Liability")>0,"Yes","No") -> No | R13: =IF(AND($Q13="Yes",$F13<>"Liability"),"Cross-Sold","")
A14: PL 517 | B14: 190 | C14: Offline | D14: Not POS | E14: Bajaj Allianz General Insurance Co Ltd | F14: =VLOOKUP(G14,'Policy Type'!$A:$B,2,FALSE) -> P&C | G14: Private Car | H14: 45169 | I14: 45534 | J14: 768298 | K14: =J14*0.18 -> 138293.64 | L14: =J14+K14 -> 906591.64 | M14: =L14*0.2 -> 181318.33 | N14: Retail | O14: Renew | P14: =IF(COUNTIF(B:B,B14)=1,"New Client","Old Client") -> New Client | Q14: =IF(COUNTIFS($B:$B,$B14,$F:$F,"Liability")>0,"Yes","No") -> No | R14: =IF(AND($Q14="Yes",$F14<>"Liability"),"Cross-Sold","")
A15: PL 522 | B15: 193 | C15: BD | D15: Not POS | E15: Bajaj Allianz General Insurance Co Ltd | F15: =VLOOKUP(G15,'Policy Type'!$A:$B,2,FALSE) -> P&C | G15: Two Wheeler | H15: 45141 | I15: 45506 | J15: 161306 | K15: =J15*0.18 -> 29035.08 | L15: =J15+K15 -> 190341.08 | M15: =L15*0.2 -> 38068.216 | N15: Retail | O15: Rollover | P15: =IF(COUNTIF(B:B,B15)=1,"New Client","Old Client") -> Old Client | Q15: =IF(COUNTIFS($B:$B,$B15,$F:$F,"Liability")>0,"Yes","No") -> No | R15: =IF(AND($Q15="Yes",$F15<>"Liability"),"Cross-Sold","")
A16: PL 524 | B16: 191 | C16: BD | D16: Not POS | E16: Bajaj Allianz General Insurance Co Ltd | F16: =VLOOKUP(G16,'Policy Type'!$A:$B,2,FALSE) -> P&C | G16: Two Wheeler - OD | H16: 45141 | I16: 45506 | J16: 109100 | K16: =J16*0.18 -> 19638 | L16: =J16+K16 -> 128738 | M16: =L16*0.2 -> 25747.6 | N16: Retail | O16: Rollover | P16: =IF(COUNTIF(B:B,B16)=1,"New Client","Old Client") -> New Client | Q16: =IF(COUNTIFS($B:$B,$B16,$F:$F,"Liability")>0,"Yes","No") -> No | R16: =IF(AND($Q16="Yes",$F16<>"Liability"),"Cross-Sold","")
A17: PL 526 | B17: 121 | C17: Ads | D17: Not POS | E17: Bajaj Allianz General Insurance Co Ltd | F17: =VLOOKUP(G17,'Policy Type'!$A:$B,2,FALSE) -> P&C | G17: Private Car | H17: 45144 | I17: 45509 | J17: 2905396 | K17: =J17*0.18 -> 522971.28 | L17: =J17+K17 -> 3428367.3 | M17: =L17*0.2 -> 685673.46 | N17: Retail | O17: Rollover | P17: =IF(COUNTIF(B:B,B17)=1,"New Client","Old Client") -> New Client | Q17: =IF(COUNTIFS($B:$B,$B17,$F:$F,"Liability")>0,"Yes","No") -> No | R17: =IF(AND($Q17="Yes",$F17<>"Liability"),"Cross-Sold","")
A18: PL 528 | B18: 194 | C18: Offline | D18: Not POS | E18: Bajaj Allianz General Insurance Co Ltd | F18: =VLOOKUP(G18,'Policy Type'!$A:$B,2,FALSE) -> P&C | G18: Two Wheeler - OD | H18: 45148 | I18: 45513 | J18: 92200 | K18: =J18*0.18 -> 16596 | L18: =J18+K18 -> 108796 | M18: =L18*0.2 -> 21759.2 | N18: Retail | O18: Rollover | P18: =IF(COUNTIF(B:B,B18)=1,"New Client","Old Client") -> Old Client | Q18: =IF(COUNTIFS($B:$B,$B18,$F:$F,"Liability")>0,"Yes","No") -> No | R18: =IF(AND($Q18="Yes",$F18<>"Liability"),"Cross-Sold","")
A19: PL 530 | B19: 195 | C19: POS | D19: Mumbai | E19: Bajaj Allianz General Insurance Co Ltd | F19: =VLOOKUP(G19,'Policy Type'!$A:$B,2,FALSE) -> P&C | G19: Private Car | H19: 45152 | I19: 45517 | J19: 698324 | K19: =J19*0.18 -> 125698.32 | L19: =J19+K19 -> 824022.32 | M19: =L19*0.05 -> 41201.116 | N19: Retail | O19: Rollover | P19: =IF(COUNTIF(B:B,B19)=1,"New Client","Old Client") -> New Client | Q19: =IF(COUNTIFS($B:$B,$B19,$F:$F,"Liability")>0,"Yes","No") -> No | R19: =IF(AND($Q19="Yes",$F19<>"Liability"),"Cross-Sold","")
A20: PL 532 | B20: 196 | C20: Offline | D20: Not POS | E20: ICICI Lombard General Insurance Co Ltd | F20: =VLOOKUP(G20,'Policy Type'!$A:$B,2,FALSE) -> P&C | G20: Private Car | H20: 45149 | I20: 45514 | J20: 1326556 | K20: =J20*0.18 -> 238780.08 | L20: =J20+K20 -> 1565336.1 | M20: =L20*0.2 -> 313067.22 | N20: Retail | O20: Rollover | P20: =IF(COUNTIF(B:B,B20)=1,"New Client","Old Client") -> New Client | Q20: =IF(COUNTIFS($B:$B,$B20,$F:$F,"Liability")>0,"Yes","No") -> No | R20: =IF(AND($Q20="Yes",$F20<>"Liability"),"Cross-Sold","")
A21: PL 534 | B21: 107 | C21: POS | D21: Nagpur | E21: Future Generali India Insurance Co Ltd | F21: =VLOOKUP(G21,'Policy Type'!$A:$B,2,FALSE) -> P&C | G21: Specific Marine | H21: 45139 | I21: 45139 | J21: 106300 | K21: =J21*0.18 -> 19134 | L21: =J21+K21 -> 125434 | M21: =L21*0.05 -> 6271.7 | N21: Corporate | O21: New | P21: =IF(COUNTIF(B:B,B21)=1,"New Client","Old Client") -> Old Client | Q21: =IF(COUNTIFS($B:$B,$B21,$F:$F,"Liability")>0,"Yes","No") -> No | R21: =IF(AND($Q21="Yes",$F21<>"Liability"),"Cross-Sold","")
A22: PL 536 | B22: 70 | C22: Offline | D22: Not POS | E22: ICICI Lombard General Insurance Co Ltd | F22: =VLOOKUP(G22,'Policy Type'!$A:$B,2,FALSE) -> P&C | G22: Marine Open | H22: 45139 | I22: 45504 | J22: 11800100 | K22: =J22*0.18 -> 2124018 | L22: =J22+K22 -> 13924118 | M22: =L22*0.2 -> 2784823.6 | N22: Corporate | O22: New | P22: =IF(COUNTIF(B:B,B22)=1,"New Client","Old Client") -> Old Client | Q22: =IF(COUNTIFS($B:$B,$B22,$F:$F,"Liability")>0,"Yes","No") -> Yes | R22: =IF(AND($Q22="Yes",$F22<>"Liability"),"Cross-Sold","") -> Cross-Sold
A23: PL 538 | B23: 197 | C23: Ads | D23: Not POS | E23: Future Generali India Insurance Co Ltd | F23: =VLOOKUP(G23,'Policy Type'!$A:$B,2,FALSE) -> P&C | G23: Specific Marine | H23: 45140 | I23: 45140 | J23: 604500 | K23: =J23*0.18 -> 108810 | L23: =J23+K23 -> 713310 | M23: =L23*0.2 -> 142662 | N23: Corporate | O23: New | P23: =IF(COUNTIF(B:B,B23)=1,"New Client","Old Client") -> Old Client | Q23: =IF(COUNTIFS($B:$B,$B23,$F:$F,"Liability")>0,"Yes","No") -> Yes | R23: =IF(AND($Q23="Yes",$F23<>"Liability"),"Cross-Sold","") -> Cross-Sold
A24: PL 540 | B24: 198 | C24: Offline | D24: Not POS | E24: HDFC Ergo General Insurance Co Ltd | F24: =VLOOKUP(G24,'Policy Type'!$A:$B,2,FALSE) -> Liability | G24: D & O | H24: 45157 | I24: 45522 | J24: 1770000 | K24: =J24*0.18 -> 318600 | L24: =J24+K24 -> 2088600 | M24: =L24*0.2 -> 417720 | N24: Corporate | O24: Rollover | P24: =IF(COUNTIF(B:B,B24)=1,"New Client","Old Client") -> Old Client | Q24: =IF(COUNTIFS($B:$B,$B24,$F:$F,"Liability")>0,"Yes","No") -> Yes | R24: =IF(AND($Q24="Yes",$F24<>"Liability"),"Cross-Sold","")
A25: PL 541 | B25: 198 | C25: BD | D25: Not POS | E25: HDFC Ergo General Insurance Co Ltd | F25: =VLOOKUP(G25,'Policy Type'!$A:$B,2,FALSE) -> Liability | G25: E & O | H25: 45157 | I25: 45522 | J25: 4720000 | K25: =J25*0.18 -> 849600 | L25: =J25+K25 -> 5569600 | M25: =L25*0.2 -> 1113920 | N25: Corporate | O25: Rollover | P25: =IF(COUNTIF(B:B,B25)=1,"New Client","Old Client") -> Old Client | Q25: =IF(COUNTIFS($B:$B,$B25,$F:$F,"Liability")>0,"Yes","No") -> Yes | R25: =IF(AND($Q25="Yes",$F25<>"Liability"),"Cross-Sold","")
A26: PL 542 | B26: 199 | C26: POS | D26: Indore | E26: Bajaj Allianz General Insurance Co Ltd | F26: =VLOOKUP(G26,'Policy Type'!$A:$B,2,FALSE) -> P&C | G26: Star Package | H26: 45167 | I26: 45532 | J26: 1965400 | K26: =J26*0.18 -> 353772 | L26: =J26+K26 -> 2319172 | M26: =L26*0.05 -> 115958.6 | N26: Retail | O26: Rollover | P26: =IF(COUNTIF(B:B,B26)=1,"New Client","Old Client") -> Old Client | Q26: =IF(COUNTIFS($B:$B,$B26,$F:$F,"Liability")>0,"Yes","No") -> Yes | R26: =IF(AND($Q26="Yes",$F26<>"Liability"),"Cross-Sold","") -> Cross-Sold
A27: PL 543 | B27: 117 | C27: Ads | D27: Not POS | E27: Cholamandalam MS General Insurance | F27: =VLOOKUP(G27,'Policy Type'!$A:$B,2,FALSE) -> P&C | G27: Shopkeeper | H27: 45140 | I27: 45505 | J27: 2245000 | K27: =J27*0.18 -> 404100 | L27: =J27+K27 -> 2649100 | M27: =L27*0.2 -> 529820 | N27: Corporate | O27: New | P27: =IF(COUNTIF(B:B,B27)=1,"New Client","Old Client") -> Old Client | Q27: =IF(COUNTIFS($B:$B,$B27,$F:$F,"Liability")>0,"Yes","No") -> Yes | R27: =IF(AND($Q27="Yes",$F27<>"Liability"),"Cross-Sold","") -> Cross-Sold
A28: PL 545 | B28: 200 | C28: BD | D28: Not POS | E28: HDFC Ergo General Insurance Co Ltd | F28: =VLOOKUP(G28,'Policy Type'!$A:$B,2,FALSE) -> Liability | G28: Public Liability | H28: 45140 | I28: 45505 | J28: 1062000 | K28: =J28*0.18 -> 191160 | L28: =J28+K28 -> 1253160 | M28: =L28*0.2 -> 250632 | N28: Corporate | O28: New | P28: =IF(COUNTIF(B:B,B28)=1,"New Client","Old Client") -> Old Client | Q28: =IF(COUNTIFS($B:$B,$B28,$F:$F,"Liability")>0,"Yes","No") -> Yes | R28: =IF(AND($Q28="Yes",$F28<>"Liability"),"Cross-Sold","")
A29: PL 546 | B29: 201 | C29: POS | D29: Ahemdabad | E29: Future Generali India Insurance Co Ltd | F29: =VLOOKUP(G29,'Policy Type'!$A:$B,2,FALSE) -> P&C | G29: Specific Marine | H29: 45140 | I29: 45140 | J29: 115000 | K29: =J29*0.18 -> 20700 | L29: =J29+K29 -> 135700 | M29: =L29*0.05 -> 6785 | N29: Corporate | O29: New | P29: =IF(COUNTIF(B:B,B29)=1,"New Client","Old Client") -> Old Client | Q29: =IF(COUNTIFS($B:$B,$B29,$F:$F,"Liability")>0,"Yes","No") -> No | R29: =IF(AND($Q29="Yes",$F29<>"Liability"),"Cross-Sold","")
A30: PL 547 | B30: 202 | C30: Offline | D30: Not POS | E30: Cholamandalam MS General Insurance | F30: =VLOOKUP(G30,'Policy Type'!$A:$B,2,FALSE) -> Liability | G30: Workmen Compensation | H30: 45141 | I30: 45506 | J30: 336400 | K30: =J30*0.18 -> 60552 | L30: =J30+K30 -> 396952 | M30: =L30*0.2 -> 79390.4 | N30: Corporate | O30: New | P30: =IF(COUNTIF(B:B,B30)=1,"New Client","Old Client") -> Old Client | Q30: =IF(COUNTIFS($B:$B,$B30,$F:$F,"Liability")>0,"Yes","No") -> Yes | R30: =IF(AND($Q30="Yes",$F30<>"Liability"),"Cross-Sold","")
A31: PL 548 | B31: 200 | C31: Offline | D31: Not POS | E31: HDFC Ergo General Insurance Co Ltd | F31: =VLOOKUP(G31,'Policy Type'!$A:$B,2,FALSE) -> P&C | G31: Bharat Sookshma Udyam Suraksha | H31: 45141 | I31: 45506 | J31: 1301500 | K31: =J31*0.18 -> 234270 | L31: =J31+K31 -> 1535770 | M31: =L31*0.2 -> 307154 | N31: Corporate | O31: New | P31: =IF(COUNTIF(B:B,B31)=1,"New Client","Old Client") -> Old Client | Q31: =IF(COUNTIFS($B:$B,$B31,$F:$F,"Liability")>0,"Yes","No") -> Yes | R31: =IF(AND($Q31="Yes",$F31<>"Liability"),"Cross-Sold","") -> Cross-Sold
A32: PL 549 | B32: 203 | C32: POS | D32: Mumbai | E32: HDFC Ergo General Insurance Co Ltd | F32: =VLOOKUP(G32,'Policy Type'!$A:$B,2,FALSE) -> Liability | G32: D & O | H32: 45141 | I32: 45506 | J32: 1062000 | K32: =J32*0.18 -> 191160 | L32: =J32+K32 -> 1253160 | M32: =L32*0.05 -> 62658 | N32: Corporate | O32: New | P32: =IF(COUNTIF(B:B,B32)=1,"New Client","Old Client") -> Old Client | Q32: =IF(COUNTIFS($B:$B,$B32,$F:$F,"Liability")>0,"Yes","No") -> Yes | R32: =IF(AND($Q32="Yes",$F32<>"Liability"),"Cross-Sold","")
A33: PL 550 | B33: 203 | C33: Offline | D33: Not POS | E33: HDFC Ergo General Insurance Co Ltd | F33: =VLOOKUP(G33,'Policy Type'!$A:$B,2,FALSE) -> Liability | G33: Commercial General Liability | H33: 45141 | I33: 45506 | J33: 826000 | K33: =J33*0.18 -> 148680 | L33: =J33+K33 -> 974680 | M33: =L33*0.2 -> 194936 | N33: Corporate | O33: New | P33: =IF(COUNTIF(B:B,B33)=1,"New Client","Old Client") -> Old Client | Q33: =IF(COUNTIFS($B:$B,$B33,$F:$F,"Liability")>0,"Yes","No") -> Yes | R33: =IF(AND($Q33="Yes",$F33<>"Liability"),"Cross-Sold","")
A34: PL 551 | B34: 204 | C34: Offline | D34: Not POS | E34: New India Assurance company | F34: =VLOOKUP(G34,'Policy Type'!$A:$B,2,FALSE) -> P&C | G34: Bharat Sookshma Udyam Suraksha | H34: 45142 | I34: 45507 | J34: 4864000 | K34: =J34*0.18 -> 875520 | L34: =J34+K34 -> 5739520 | M34: =L34*0.2 -> 1147904 | N34: Corporate | O34: New | P34: =IF(COUNTIF(B:B,B34)=1,"New Client","Old Client") -> New Client | Q34: =IF(COUNTIFS($B:$B,$B34,$F:$F,"Liability")>0,"Yes","No") -> No | R34: =IF(AND($Q34="Yes",$F34<>"Liability"),"Cross-Sold","")
A35: PL 552 | B35: 116 | C35: POS | D35: Indore | E35: ICICI Lombard General Insurance Co Ltd | F35: =VLOOKUP(G35,'Policy Type'!$A:$B,2,FALSE) -> Liability | G35: Cyber Crime | H35: 45141 | I35: 45506 | J35: 42477100 | K35: =J35*0.18 -> 7645878 | L35: =J35+K35 -> 50122978 | M35: =L35*0.05 -> 2506148.9 | N35: Corporate | O35: New | P35: =IF(COUNTIF(B:B,B35)=1,"New Client","Old Client") -> Old Client | Q35: =IF(COUNTIFS($B:$B,$B35,$F:$F,"Liability")>0,"Yes","No") -> Yes | R35: =IF(AND($Q35="Yes",$F35<>"Liability"),"Cross-Sold","")
A36: PL 553 | B36: 15 | C36: Ads | D36: Not POS | E36: Future Generali India Insurance Co Ltd | F36: =VLOOKUP(G36,'Policy Type'!$A:$B,2,FALSE) -> P&C | G36: Specific Marine | H36: 45143 | I36: 45143 | J36: 212900 | K36: =J36*0.18 -> 38322 | L36: =J36+K36 -> 251222 | M36: =L36*0.2 -> 50244.4 | N36: Corporate | O36: New | P36: =IF(COUNTIF(B:B,B36)=1,"New Client","Old Client") -> Old Client | Q36: =IF(COUNTIFS($B:$B,$B36,$F:$F,"Liability")>0,"Yes","No") -> Yes | R36: =IF(AND($Q36="Yes",$F36<>"Liability"),"Cross-Sold","") -> Cross-Sold
A37: PL 554 | B37: 205 | C37: Offline | D37: Not POS | E37: SBI General Insurance Co Ltd | F37: =VLOOKUP(G37,'Policy Type'!$A:$B,2,FALSE) -> Liability | G37: Public Liability | H37: 45145 | I37: 45510 | J37: 295000 | K37: =J37*0.18 -> 53100 | L37: =J37+K37 -> 348100 | M37: =L37*0.2 -> 69620 | N37: Corporate | O37: New | P37: =IF(COUNTIF(B:B,B37)=1,"New Client","Old Client") -> New Client | Q37: =IF(COUNTIFS($B:$B,$B37,$F:$F,"Liability")>0,"Yes","No") -> Yes | R37: =IF(AND($Q37="Yes",$F37<>"Liability"),"Cross-Sold","")
A38: PL 555 | B38: 206 | C38: BD | D38: Not POS | E38: Future Generali India Insurance Co Ltd | F38: =VLOOKUP(G38,'Policy Type'!$A:$B,2,FALSE) -> P&C | G38: Specific Marine | H38: 45145 | I38: 45145 | J38: 67300 | K38: =J38*0.18 -> 12114 | L38: =J38+K38 -> 79414 | M38: =L38*0.2 -> 15882.8 | N38: Corporate | O38: New | P38: =IF(COUNTIF(B:B,B38)=1,"New Client","Old Client") -> Old Client | Q38: =IF(COUNTIFS($B:$B,$B38,$F:$F,"Liability")>0,"Yes","No") -> No | R38: =IF(AND($Q38="Yes",$F38<>"Liability"),"Cross-Sold","")
A39: PL 556 | B39: 207 | C39: POS | D39: Mumbai | E39: Bajaj Allianz General Insurance Co Ltd | F39: =VLOOKUP(G39,'Policy Type'!$A:$B,2,FALSE) -> Others | G39: Travel | H39: 45172 | I39: 45231 | J39: 250600 | K39: =J39*0.18 -> 45108 | L39: =J39+K39 -> 295708 | M39: =L39*0.05 -> 14785.4 | N39: Retail | O39: New | P39: =IF(COUNTIF(B:B,B39)=1,"New Client","Old Client") -> Old Client | Q39: =IF(COUNTIFS($B:$B,$B39,$F:$F,"Liability")>0,"Yes","No") -> Yes | R39: =IF(AND($Q39="Yes",$F39<>"Liability"),"Cross-Sold","") -> Cross-Sold
A40: PL 557 | B40: 208 | C40: Offline | D40: Not POS | E40: Bajaj Allianz General Insurance Co Ltd | F40: =VLOOKUP(G40,'Policy Type'!$A:$B,2,FALSE) -> Others | G40: Travel | H40: 45182 | I40: 45228 | J40: 213800 | K40: =J40*0.18 -> 38484 | L40: =J40+K40 -> 252284 | M40: =L40*0.15 -> 37842.6 | N40: Retail | O40: New | P40: =IF(COUNTIF(B:B,B40)=1,"New Client","Old Client") -> New Client | Q40: =IF(COUNTIFS($B:$B,$B40,$F:$F,"Liability")>0,"Yes","No") -> No | R40: =IF(AND($Q40="Yes",$F40<>"Liability"),"Cross-Sold","")
A41: PL 558 | B41: 63 | C41: POS | D41: Nagpur | E41: Bajaj Allianz General Insurance Co Ltd | F41: =VLOOKUP(G41,'Policy Type'!$A:$B,2,FALSE) -> Liability | G41: Workmen Compensation | H41: 45145 | I41: 45510 | J41: 767400 | K41: =J41*0.18 -> 138132 | L41: =J41+K41 -> 905532 | M41: =L41*0.05 -> 45276.6 | N41: Corporate | O41: New | P41: =IF(COUNTIF(B:B,B41)=1,"New Client","Old Client") -> Old Client | Q41: =IF(COUNTIFS($B:$B,$B41,$F:$F,"Liability")>0,"Yes","No") -> Yes | R41: =IF(AND($Q41="Yes",$F41<>"Liability"),"Cross-Sold","")
A42: PL 559 | B42: 209 | C42: BD | D42: Not POS | E42: Bajaj Allianz General Insurance Co Ltd | F42: =VLOOKUP(G42,'Policy Type'!$A:$B,2,FALSE) -> P&C | G42: Two Wheeler | H42: 45146 | I42: 45511 | J42: 456306 | K42: =J42*0.18 -> 82135.08 | L42: =J42+K42 -> 538441.08 | M42: =L42*0.2 -> 107688.22 | N42: Retail | O42: New | P42: =IF(COUNTIF(B:B,B42)=1,"New Client","Old Client") -> New Client | Q42: =IF(COUNTIFS($B:$B,$B42,$F:$F,"Liability")>0,"Yes","No") -> No | R42: =IF(AND($Q42="Yes",$F42<>"Liability"),"Cross-Sold","")
A43: PL 560 | B43: 76 | C43: Offline | D43: Not POS | E43: Future Generali India Insurance Co Ltd | F43: =VLOOKUP(G43,'Policy Type'!$A:$B,2,FALSE) -> Others | G43: Erection All Risk | H43: 45147 | I43: 45244 | J43: 2451200 | K43: =J43*0.18 -> 441216 | L43: =J43+K43 -> 2892416 | M43: =L43*0.15 -> 433862.4 | N43: Corporate | O43: New | P43: =IF(COUNTIF(B:B,B43)=1,"New Client","Old Client") -> Old Client | Q43: =IF(COUNTIFS($B:$B,$B43,$F:$F,"Liability")>0,"Yes","No") -> Yes | R43: =IF(AND($Q43="Yes",$F43<>"Liability"),"Cross-Sold","") -> Cross-Sold
A44: PL 561 | B44: 210 | C44: POS | D44: Ahemdabad | E44: Future Generali India Insurance Co Ltd | F44: =VLOOKUP(G44,'Policy Type'!$A:$B,2,FALSE) -> P&C | G44: Marine Open | H44: 45148 | I44: 45513 | J44: 1401400 | K44: =J44*0.18 -> 252252 | L44: =J44+K44 -> 1653652 | M44: =L44*0.05 -> 82682.6 | N44: Corporate | O44: New | P44: =IF(COUNTIF(B:B,B44)=1,"New Client","Old Client") -> Old Client | Q44: =IF(COUNTIFS($B:$B,$B44,$F:$F,"Liability")>0,"Yes","No") -> Yes | R44: =IF(AND($Q44="Yes",$F44<>"Liability"),"Cross-Sold","") -> Cross-Sold
A45: PL 562 | B45: 51 | C45: BD | D45: Not POS | E45: Future Generali India Insurance Co Ltd | F45: =VLOOKUP(G45,'Policy Type'!$A:$B,2,FALSE) -> Others | G45: Travel | H45: 45149 | I45: 45153 | J45: 63100 | K45: =J45*0.18 -> 11358 | L45: =J45+K45 -> 74458 | M45: =L45*0.15 -> 11168.7 | N45: Retail | O45: New | P45: =IF(COUNTIF(B:B,B45)=1,"New Client","Old Client") -> Old Client | Q45: =IF(COUNTIFS($B:$B,$B45,$F:$F,"Liability")>0,"Yes","No") -> No | R45: =IF(AND($Q45="Yes",$F45<>"Liability"),"Cross-Sold","")
A46: PL 563 | B46: 211 | C46: Ads | D46: Not POS | E46: Future Generali India Insurance Co Ltd | F46: =VLOOKUP(G46,'Policy Type'!$A:$B,2,FALSE) -> P&C | G46: Specific Marine | H46: 45148 | I46: 45148 | J46: 106200 | K46: =J46*0.18 -> 19116 | L46: =J46+K46 -> 125316 | M46: =L46*0.2 -> 25063.2 | N46: Corporate | O46: New | P46: =IF(COUNTIF(B:B,B46)=1,"New Client","Old Client") -> Old Client | Q46: =IF(COUNTIFS($B:$B,$B46,$F:$F,"Liability")>0,"Yes","No") -> Yes | R46: =IF(AND($Q46="Yes",$F46<>"Liability"),"Cross-Sold","") -> Cross-Sold
A47: PL 564 | B47: 212 | C47: POS | D47: Nagpur | E47: ICICI Lombard General Insurance Co Ltd | F47: =VLOOKUP(G47,'Policy Type'!$A:$B,2,FALSE) -> Liability | G47: Group Personal Accident | H47: 45148 | I47: 45513 | J47: 703800 | K47: =J47*0.18 -> 126684 | L47: =J47+K47 -> 830484 | M47: =L47*0.05 -> 41524.2 | N47: Corporate | O47: New | P47: =IF(COUNTIF(B:B,B47)=1,"New Client","Old Client") -> Old Client | Q47: =IF(COUNTIFS($B:$B,$B47,$F:$F,"Liability")>0,"Yes","No") -> Yes | R47: =IF(AND($Q47="Yes",$F47<>"Liability"),"Cross-Sold","")
A48: PL 565 | B48: 212 | C48: BD | D48: Not POS | E48: Care Health Ltd | F48: =VLOOKUP(G48,'Policy Type'!$A:$B,2,FALSE) -> Others | G48: Group Mediclaim | H48: 45148 | I48: 45513 | J48: 7670000 | K48: =J48*0.18 -> 1380600 | L48: =J48+K48 -> 9050600 | M48: =L48*0.15 -> 1357590 | N48: Corporate | O48: New | P48: =IF(COUNTIF(B:B,B48)=1,"New Client","Old Client") -> Old Client | Q48: =IF(COUNTIFS($B:$B,$B48,$F:$F,"Liability")>0,"Yes","No") -> Yes | R48: =IF(AND($Q48="Yes",$F48<>"Liability"),"Cross-Sold","") -> Cross-Sold
A49: PL 566 | B49: 68 | C49: Offline | D49: Not POS | E49: Bajaj Allianz General Insurance Co Ltd | F49: =VLOOKUP(G49,'Policy Type'!$A:$B,2,FALSE) -> Others | G49: Bharat Laghu Udyam Suraksha | H49: 45149 | I49: 45514 | J49: 10888600 | K49: =J49*0.18 -> 1959948 | L49: =J49+K49 -> 12848548 | M49: =L49*0.15 -> 1927282.2 | N49: Corporate | O49: New | P49: =IF(COUNTIF(B:B,B49)=1,"New Client","Old Client") -> Old Client | Q49: =IF(COUNTIFS($B:$B,$B49,$F:$F,"Liability")>0,"Yes","No") -> Yes | R49: =IF(AND($Q49="Yes",$F49<>"Liability"),"Cross-Sold","") -> Cross-Sold
A50: PL 567 | B50: 68 | C50: Offline | D50: Not POS | E50: Bajaj Allianz General Insurance Co Ltd | F50: =VLOOKUP(G50,'Policy Type'!$A:$B,2,FALSE) -> P&C | G50: Burglary | H50: 45149 | I50: 45514 | J50: 1793600 | K50: =J50*0.18 -> 322848 | L50: =J50+K50 -> 2116448 | M50: =L50*0.2 -> 423289.6 | N50: Corporate | O50: New | P50: =IF(COUNTIF(B:B,B50)=1,"New Client","Old Client") -> Old Client | Q50: =IF(COUNTIFS($B:$B,$B50,$F:$F,"Liability")>0,"Yes","No") -> Yes | R50: =IF(AND($Q50="Yes",$F50<>"Liability"),"Cross-Sold","") -> Cross-Sold
A51: PL 568 | B51: 213 | C51: Offline | D51: Not POS | E51: Future Generali India Insurance Co Ltd | F51: =VLOOKUP(G51,'Policy Type'!$A:$B,2,FALSE) -> Others | G51: Contractor's Plant and Machinery | H51: 45149 | I51: 45514 | J51: 587600 | K51: =J51*0.18 -> 105768 | L51: =J51+K51 -> 693368 | M51: =L51*0.15 -> 104005.2 | N51: Corporate | O51: New | P51: =IF(COUNTIF(B:B,B51)=1,"New Client","Old Client") -> Old Client | Q51: =IF(COUNTIFS($B:$B,$B51,$F:$F,"Liability")>0,"Yes","No") -> Yes | R51: =IF(AND($Q51="Yes",$F51<>"Liability"),"Cross-Sold","") -> Cross-Sold
A52: PL 569 | B52: 32 | C52: POS | D52: Ahemdabad | E52: Future Generali India Insurance Co Ltd | F52: =VLOOKUP(G52,'Policy Type'!$A:$B,2,FALSE) -> Liability | G52: Group Personal Accident | H52: 45149 | I52: 45514 | J52: 500300 | K52: =J52*0.18 -> 90054 | L52: =J52+K52 -> 590354 | M52: =L52*0.05 -> 29517.7 | N52: Corporate | O52: New | P52: =IF(COUNTIF(B:B,B52)=1,"New Client","Old Client") -> Old Client | Q52: =IF(COUNTIFS($B:$B,$B52,$F:$F,"Liability")>0,"Yes","No") -> Yes | R52: =IF(AND($Q52="Yes",$F52<>"Liability"),"Cross-Sold","")
A53: PL 570 | B53: 214 | C53: BD | D53: Not POS | E53: TATA AIG General Insurance Co Ltd | F53: =VLOOKUP(G53,'Policy Type'!$A:$B,2,FALSE) -> Others | G53: Travel | H53: 45154 | I53: 45244 | J53: 733000 | K53: =J53*0.18 -> 131940 | L53: =J53+K53 -> 864940 | M53: =L53*0.15 -> 129741 | N53: Retail | O53: New | P53: =IF(COUNTIF(B:B,B53)=1,"New Client","Old Client") -> New Client | Q53: =IF(COUNTIFS($B:$B,$B53,$F:$F,"Liability")>0,"Yes","No") -> No | R53: =IF(AND($Q53="Yes",$F53<>"Liability"),"Cross-Sold","")
A54: PL 571 | B54: 15 | C54: Offline | D54: Not POS | E54: Future Generali India Insurance Co Ltd | F54: =VLOOKUP(G54,'Policy Type'!$A:$B,2,FALSE) -> P&C | G54: Specific Marine | H54: 45150 | I54: 45150 | J54: 176700 | K54: =J54*0.18 -> 31806 | L54: =J54+K54 -> 208506 | M54: =L54*0.2 -> 41701.2 | N54: Corporate | O54: New | P54: =IF(COUNTIF(B:B,B54)=1,"New Client","Old Client") -> Old Client | Q54: =IF(COUNTIFS($B:$B,$B54,$F:$F,"Liability")>0,"Yes","No") -> Yes | R54: =IF(AND($Q54="Yes",$F54<>"Liability"),"Cross-Sold","") -> Cross-Sold
A55: PL 572 | B55: 215 | C55: BD | D55: Not POS | E55: Cholamandalam MS General Insurance | F55: =VLOOKUP(G55,'Policy Type'!$A:$B,2,FALSE) -> Others | G55: Office Package | H55: 45150 | I55: 45515 | J55: 338100 | K55: =J55*0.18 -> 60858 | L55: =J55+K55 -> 398958 | M55: =L55*0.15 -> 59843.7 | N55: Corporate | O55: New | P55: =IF(COUNTIF(B:B,B55)=1,"New Client","Old Client") -> New Client | Q55: =IF(COUNTIFS($B:$B,$B55,$F:$F,"Liability")>0,"Yes","No") -> No | R55: =IF(AND($Q55="Yes",$F55<>"Liability"),"Cross-Sold","")
A56: PL 573 | B56: 216 | C56: Ads | D56: Not POS | E56: Cholamandalam MS General Insurance | F56: =VLOOKUP(G56,'Policy Type'!$A:$B,2,FALSE) -> Others | G56: Office Package | H56: 45154 | I56: 45519 | J56: 1356300 | K56: =J56*0.18 -> 244134 | L56: =J56+K56 -> 1600434 | M56: =L56*0.15 -> 240065.1 | N56: Corporate | O56: New | P56: =IF(COUNTIF(B:B,B56)=1,"New Client","Old Client") -> New Client | Q56: =IF(COUNTIFS($B:$B,$B56,$F:$F,"Liability")>0,"Yes","No") -> No | R56: =IF(AND($Q56="Yes",$F56<>"Liability"),"Cross-Sold","")
A57: PL 574 | B57: 217 | C57: POS | D57: Indore | E57: HDFC Ergo General Insurance Co Ltd | F57: =VLOOKUP(G57,'Policy Type'!$A:$B,2,FALSE) -> Liability | G57: D & O | H57: 45155 | I57: 45520 | J57: 12390000 | K57: =J57*0.18 -> 2230200 | L57: =J57+K57 -> 14620200 | M57: =L57*0.05 -> 731010 | N57: Corporate | O57: New | P57: =IF(COUNTIF(B:B,B57)=1,"New Client","Old Client") -> New Client | Q57: =IF(COUNTIFS($B:$B,$B57,$F:$F,"Liability")>0,"Yes","No") -> Yes | R57: =IF(AND($Q57="Yes",$F57<>"Liability"),"Cross-Sold","")
A58: PL 576 | B58: 218 | C58: BD | D58: Not POS | E58: HDFC Ergo General Insurance Co Ltd | F58: =VLOOKUP(G58,'Policy Type'!$A:$B,2,FALSE) -> Liability | G58: Commercial General Liability | H58: 45155 | I58: 45520 | J58: 531000 | K58: =J58*0.18 -> 95580 | L58: =J58+K58 -> 626580 | M58: =L58*0.2 -> 125316 | N58: Corporate | O58: New | P58: =IF(COUNTIF(B:B,B58)=1,"New Client","Old Client") -> Old Client | Q58: =IF(COUNTIFS($B:$B,$B58,$F:$F,"Liability")>0,"Yes","No") -> Yes | R58: =IF(AND($Q58="Yes",$F58<>"Liability"),"Cross-Sold","")
A59: PL 577 | B59: 218 | C59: Offline | D59: Not POS | E59: HDFC Ergo General Insurance Co Ltd | F59: =VLOOKUP(G59,'Policy Type'!$A:$B,2,FALSE) -> Liability | G59: Professional Indemnity | H59: 45155 | I59: 45520 | J59: 1180000 | K59: =J59*0.18 -> 212400 | L59: =J59+K59 -> 1392400 | M59: =L59*0.2 -> 278480 | N59: Corporate | O59: New | P59: =IF(COUNTIF(B:B,B59)=1,"New Client","Old Client") -> Old Client | Q59: =IF(COUNTIFS($B:$B,$B59,$F:$F,"Liability")>0,"Yes","No") -> Yes | R59: =IF(AND($Q59="Yes",$F59<>"Liability"),"Cross-Sold","")
A60: PL 578 | B60: 218 | C60: Ads | D60: Not POS | E60: HDFC Ergo General Insurance Co Ltd | F60: =VLOOKUP(G60,'Policy Type'!$A:$B,2,FALSE) -> Liability | G60: Workmen Compensation | H60: 45156 | I60: 45521 | J60: 505000 | K60: =J60*0.18 -> 90900 | L60: =J60+K60 -> 595900 | M60: =L60*0.2 -> 119180 | N60: Corporate | O60: New | P60: =IF(COUNTIF(B:B,B60)=1,"New Client","Old Client") -> Old Client | Q60: =IF(COUNTIFS($B:$B,$B60,$F:$F,"Liability")>0,"Yes","No") -> Yes | R60: =IF(AND($Q60="Yes",$F60<>"Liability"),"Cross-Sold","")
A61: PL 579 | B61: 219 | C61: Offline | D61: Not POS | E61: Future Generali India Insurance Co Ltd | F61: =VLOOKUP(G61,'Policy Type'!$A:$B,2,FALSE) -> P&C | G61: Private Car | H61: 45140 | I61: 45505 | J61: 1546154 | K61: =J61*0.18 -> 278307.72 | L61: =J61+K61 -> 1824461.7 | M61: =L61*0.2 -> 364892.34 | N61: Retail | O61: Renew | P61: =IF(COUNTIF(B:B,B61)=1,"New Client","Old Client") -> New Client | Q61: =IF(COUNTIFS($B:$B,$B61,$F:$F,"Liability")>0,"Yes","No") -> No | R61: =IF(AND($Q61="Yes",$F61<>"Liability"),"Cross-Sold","")
A62: PL 580 | B62: 220 | C62: Offline | D62: Not POS | E62: Bajaj Allianz General Insurance Co Ltd | F62: =VLOOKUP(G62,'Policy Type'!$A:$B,2,FALSE) -> P&C | G62: Two Wheeler - OD | H62: 45145 | I62: 45510 | J62: 83000 | K62: =J62*0.18 -> 14940 | L62: =J62+K62 -> 97940 | M62: =L62*0.2 -> 19588 | N62: Retail | O62: Renew | P62: =IF(COUNTIF(B:B,B62)=1,"New Client","Old Client") -> New Client | Q62: =IF(COUNTIFS($B:$B,$B62,$F:$F,"Liability")>0,"Yes","No") -> No | R62: =IF(AND($Q62="Yes",$F62<>"Liability"),"Cross-Sold","")
A63: PL 581 | B63: 221 | C63: BD | D63: Not POS | E63: Future Generali India Insurance Co Ltd | F63: =VLOOKUP(G63,'Policy Type'!$A:$B,2,FALSE) -> P&C | G63: Shopkeeper | H63: 45143 | I63: 45508 | J63: 2245200 | K63: =J63*0.18 -> 404136 | L63: =J63+K63 -> 2649336 | M63: =L63*0.2 -> 529867.2 | N63: Retail | O63: Renew | P63: =IF(COUNTIF(B:B,B63)=1,"New Client","Old Client") -> Old Client | Q63: =IF(COUNTIFS($B:$B,$B63,$F:$F,"Liability")>0,"Yes","No") -> No | R63: =IF(AND($Q63="Yes",$F63<>"Liability"),"Cross-Sold","")
A64: PL 582 | B64: 222 | C64: Ads | D64: Not POS | E64: Future Generali India Insurance Co Ltd | F64: =VLOOKUP(G64,'Policy Type'!$A:$B,2,FALSE) -> P&C | G64: Private Car | H64: 45158 | I64: 45523 | J64: 512828 | K64: =J64*0.18 -> 92309.04 | L64: =J64+K64 -> 605137.04 | M64: =L64*0.2 -> 121027.41 | N64: Retail | O64: Renew | P64: =IF(COUNTIF(B:B,B64)=1,"New Client","Old Client") -> Old Client | Q64: =IF(COUNTIFS($B:$B,$B64,$F:$F,"Liability")>0,"Yes","No") -> No | R64: =IF(AND($Q64="Yes",$F64<>"Liability"),"Cross-Sold","")
A65: PL 583 | B65: 223 | C65: POS | D65: Nagpur | E65: Future Generali India Insurance Co Ltd | F65: =VLOOKUP(G65,'Policy Type'!$A:$B,2,FALSE) -> Liability | G65: E & O | H65: 45139 | I65: 45504 | J65: 76800 | K65: =J65*0.18 -> 13824 | L65: =J65+K65 -> 90624 | M65: =L65*0.05 -> 4531.2 | N65: Retail | O65: Renew | P65: =IF(COUNTIF(B:B,B65)=1,"New Client","Old Client") -> New Client | Q65: =IF(COUNTIFS($B:$B,$B65,$F:$F,"Liability")>0,"Yes","No") -> Yes | R65: =IF(AND($Q65="Yes",$F65<>"Liability"),"Cross-Sold","")
A66: PL 584 | B66: 189 | C66: BD | D66: Not POS | E66: Future Generali India Insurance Co Ltd | F66: =VLOOKUP(G66,'Policy Type'!$A:$B,2,FALSE) -> P&C | G66: Private Car | H66: 45153 | I66: 45518 | J66: 1328900 | K66: =J66*0.18 -> 239202 | L66: =J66+K66 -> 1568102 | M66: =L66*0.2 -> 313620.4 | N66: Corporate | O66: Renew | P66: =IF(COUNTIF(B:B,B66)=1,"New Client","Old Client") -> Old Client | Q66: =IF(COUNTIFS($B:$B,$B66,$F:$F,"Liability")>0,"Yes","No") -> No | R66: =IF(AND($Q66="Yes",$F66<>"Liability"),"Cross-Sold","")
A67: PL 585 | B67: 224 | C67: POS | D67: Nagpur | E67: Cholamandalam MS General Insurance | F67: =VLOOKUP(G67,'Policy Type'!$A:$B,2,FALSE) -> P&C | G67: Bharat Sookshma Udyam Suraksha | H67: 45162 | I67: 45527 | J67: 2386000 | K67: =J67*0.18 -> 429480 | L67: =J67+K67 -> 2815480 | M67: =L67*0.05 -> 140774 | N67: Retail | O67: Renew | P67: =IF(COUNTIF(B:B,B67)=1,"New Client","Old Client") -> Old Client | Q67: =IF(COUNTIFS($B:$B,$B67,$F:$F,"Liability")>0,"Yes","No") -> No | R67: =IF(AND($Q67="Yes",$F67<>"Liability"),"Cross-Sold","")
A68: PL 586 | B68: 224 | C68: Ads | D68: Not POS | E68: Cholamandalam MS General Insurance | F68: =VLOOKUP(G68,'Policy Type'!$A:$B,2,FALSE) -> Others | G68: Bharat Griha Raksha | H68: 45164 | I68: 45529 | J68: 239900 | K68: =J68*0.18 -> 43182 | L68: =J68+K68 -> 283082 | M68: =L68*0.15 -> 42462.3 | N68: Retail | O68: Renew | P68: =IF(COUNTIF(B:B,B68)=1,"New Client","Old Client") -> Old Client | Q68: =IF(COUNTIFS($B:$B,$B68,$F:$F,"Liability")>0,"Yes","No") -> No | R68: =IF(AND($Q68="Yes",$F68<>"Liability"),"Cross-Sold","")
A69: PL 587 | B69: 225 | C69: BD | D69: Not POS | E69: Future Generali India Insurance Co Ltd | F69: =VLOOKUP(G69,'Policy Type'!$A:$B,2,FALSE) -> Others | G69: Health Suraksha | H69: 45139 | I69: 45504 | J69: 930700 | K69: =J69*0.18 -> 167526 | L69: =J69+K69 -> 1098226 | M69: =L69*0.15 -> 164733.9 | N69: Retail | O69: Renew | P69: =IF(COUNTIF(B:B,B69)=1,"New Client","Old Client") -> New Client | Q69: =IF(COUNTIFS($B:$B,$B69,$F:$F,"Liability")>0,"Yes","No") -> No | R69: =IF(AND($Q69="Yes",$F69<>"Liability"),"Cross-Sold","")
A70: PL 588 | B70: 95 | C70: POS | D70: Nagpur | E70: Future Generali India Insurance Co Ltd | F70: =VLOOKUP(G70,'Policy Type'!$A:$B,2,FALSE) -> Others | G70: Private car - OD | H70: 45141 | I70: 45506 | J70: 2633200 | K70: =J70*0.18 -> 473976 | L70: =J70+K70 -> 3107176 | M70: =L70*0.05 -> 155358.8 | N70: Retail | O70: Renew | P70: =IF(COUNTIF(B:B,B70)=1,"New Client","Old Client") -> Old Client | Q70: =IF(COUNTIFS($B:$B,$B70,$F:$F,"Liability")>0,"Yes","No") -> Yes | R70: =IF(AND($Q70="Yes",$F70<>"Liability"),"Cross-Sold","") -> Cross-Sold
A71: PL 589 | B71: 226 | C71: POS | D71: Mumbai | E71: Future Generali India Insurance Co Ltd | F71: =VLOOKUP(G71,'Policy Type'!$A:$B,2,FALSE) -> Others | G71: Personal Accident | H71: 45143 | I71: 45508 | J71: 1022800 | K71: =J71*0.18 -> 184104 | L71: =J71+K71 -> 1206904 | M71: =L71*0.05 -> 60345.2 | N71: Retail | O71: Renew | P71: =IF(COUNTIF(B:B,B71)=1,"New Client","Old Client") -> Old Client | Q71: =IF(COUNTIFS($B:$B,$B71,$F:$F,"Liability")>0,"Yes","No") -> No | R71: =IF(AND($Q71="Yes",$F71<>"Liability"),"Cross-Sold","")
A72: PL 590 | B72: 227 | C72: Offline | D72: Not POS | E72: Future Generali India Insurance Co Ltd | F72: =VLOOKUP(G72,'Policy Type'!$A:$B,2,FALSE) -> P&C | G72: Two Wheeler - OD | H72: 45160 | I72: 45525 | J72: 286500 | K72: =J72*0.18 -> 51570 | L72: =J72+K72 -> 338070 | M72: =L72*0.2 -> 67614 | N72: Retail | O72: Renew | P72: =IF(COUNTIF(B:B,B72)=1,"New Client","Old Client") -> Old Client | Q72: =IF(COUNTIFS($B:$B,$B72,$F:$F,"Liability")>0,"Yes","No") -> No | R72: =IF(AND($Q72="Yes",$F72<>"Liability"),"Cross-Sold","")
A73: PL 591 | B73: 228 | C73: BD | D73: Not POS | E73: Cholamandalam MS General Insurance | F73: =VLOOKUP(G73,'Policy Type'!$A:$B,2,FALSE) -> Liability | G73: Public Liability | H73: 45140 | I73: 45505 | J73: 1000000 | K73: =J73*0.18 -> 180000 | L73: =J73+K73 -> 1180000 | M73: =L73*0.2 -> 236000 | N73: Corporate | O73: Renew | P73: =IF(COUNTIF(B:B,B73)=1,"New Client","Old Client") -> New Client | Q73: =IF(COUNTIFS($B:$B,$B73,$F:$F,"Liability")>0,"Yes","No") -> Yes | R73: =IF(AND($Q73="Yes",$F73<>"Liability"),"Cross-Sold","")
A74: PL 592 | B74: 229 | C74: POS | D74: Indore | E74: Bajaj Allianz General Insurance Co Ltd | F74: =VLOOKUP(G74,'Policy Type'!$A:$B,2,FALSE) -> Others | G74: Health Guard | H74: 45161 | I74: 45526 | J74: 3705200 | K74: =J74*0.18 -> 666936 | L74: =J74+K74 -> 4372136 | M74: =L74*0.05 -> 218606.8 | N74: Retail | O74: Renew | P74: =IF(COUNTIF(B:B,B74)=1,"New Client","Old Client") -> New Client | Q74: =IF(COUNTIFS($B:$B,$B74,$F:$F,"Liability")>0,"Yes","No") -> No | R74: =IF(AND($Q74="Yes",$F74<>"Liability"),"Cross-Sold","")
A75: PL 593 | B75: 230 | C75: Ads | D75: Not POS | E75: Bajaj Allianz General Insurance Co Ltd | F75: =VLOOKUP(G75,'Policy Type'!$A:$B,2,FALSE) -> P&C | G75: Two Wheeler | H75: 45145 | I75: 45510 | J75: 132986 | K75: =J75*0.18 -> 23937.48 | L75: =J75+K75 -> 156923.48 | M75: =L75*0.2 -> 31384.696 | N75: Retail | O75: Renew | P75: =IF(COUNTIF(B:B,B75)=1,"New Client","Old Client") -> New Client | Q75: =IF(COUNTIFS($B:$B,$B75,$F:$F,"Liability")>0,"Yes","No") -> No | R75: =IF(AND($Q75="Yes",$F75<>"Liability"),"Cross-Sold","")
A76: PL 594 | B76: 231 | C76: Ads | D76: Not POS | E76: Bajaj Allianz General Insurance Co Ltd | F76: =VLOOKUP(G76,'Policy Type'!$A:$B,2,FALSE) -> P&C | G76: Shopkeeper | H76: 45146 | I76: 45511 | J76: 10333900 | K76: =J76*0.18 -> 1860102 | L76: =J76+K76 -> 12194002 | M76: =L76*0.2 -> 2438800.4 | N76: Corporate | O76: Renew | P76: =IF(COUNTIF(B:B,B76)=1,"New Client","Old Client") -> New Client | Q76: =IF(COUNTIFS($B:$B,$B76,$F:$F,"Liability")>0,"Yes","No") -> No | R76: =IF(AND($Q76="Yes",$F76<>"Liability"),"Cross-Sold","")
A77: PL 595 | B77: 232 | C77: POS | D77: Ahemdabad | E77: Bajaj Allianz General Insurance Co Ltd | F77: =VLOOKUP(G77,'Policy Type'!$A:$B,2,FALSE) -> P&C | G77: Private Car | H77: 45144 | I77: 45509 | J77: 1657700 | K77: =J77*0.18 -> 298386 | L77: =J77+K77 -> 1956086 | M77: =L77*0.05 -> 97804.3 | N77: Corporate | O77: Renew | P77: =IF(COUNTIF(B:B,B77)=1,"New Client","Old Client") -> Old Client | Q77: =IF(COUNTIFS($B:$B,$B77,$F:$F,"Liability")>0,"Yes","No") -> Yes | R77: =IF(AND($Q77="Yes",$F77<>"Liability"),"Cross-Sold","") -> Cross-Sold
A78: PL 596 | B78: 233 | C78: BD | D78: Not POS | E78: Bajaj Allianz General Insurance Co Ltd | F78: =VLOOKUP(G78,'Policy Type'!$A:$B,2,FALSE) -> P&C | G78: Private Car | H78: 45163 | I78: 45528 | J78: 615134 | K78: =J78*0.18 -> 110724.12 | L78: =J78+K78 -> 725858.12 | M78: =L78*0.2 -> 145171.62 | N78: Retail | O78: Renew | P78: =IF(COUNTIF(B:B,B78)=1,"New Client","Old Client") -> Old Client | Q78: =IF(COUNTIFS($B:$B,$B78,$F:$F,"Liability")>0,"Yes","No") -> Yes | R78: =IF(AND($Q78="Yes",$F78<>"Liability"),"Cross-Sold","") -> Cross-Sold
A79: PL 597 | B79: 210 | C79: Ads | D79: Not POS | E79: Future Generali India Insurance Co Ltd | F79: =VLOOKUP(G79,'Policy Type'!$A:$B,2,FALSE) -> P&C | G79: Private Car | H79: 45152 | I79: 45517 | J79: 986362 | K79: =J79*0.18 -> 177545.16 | L79: =J79+K79 -> 1163907.2 | M79: =L79*0.2 -> 232781.43 | N79: Corporate | O79: Renew | P79: =IF(COUNTIF(B:B,B79)=1,"New Client","Old Client") -> Old Client | Q79: =IF(COUNTIFS($B:$B,$B79,$F:$F,"Liability")>0,"Yes","No") -> Yes | R79: =IF(AND($Q79="Yes",$F79<>"Liability"),"Cross-Sold","") -> Cross-Sold
A80: PL 598 | B80: 234 | C80: Ads | D80: Not POS | E80: Future Generali India Insurance Co Ltd | F80: =VLOOKUP(G80,'Policy Type'!$A:$B,2,FALSE) -> P&C | G80: Marine Open | H80: 45142 | I80: 45507 | J80: 3540000 | K80: =J80*0.18 -> 637200 | L80: =J80+K80 -> 4177200 | M80: =L80*0.2 -> 835440 | N80: Corporate | O80: Renew | P80: =IF(COUNTIF(B:B,B80)=1,"New Client","Old Client") -> Old Client | Q80: =IF(COUNTIFS($B:$B,$B80,$F:$F,"Liability")>0,"Yes","No") -> Yes | R80: =IF(AND($Q80="Yes",$F80<>"Liability"),"Cross-Sold","") -> Cross-Sold
A81: PL 599 | B81: 235 | C81: POS | D81: Indore | E81: Bajaj Allianz General Insurance Co Ltd | F81: =VLOOKUP(G81,'Policy Type'!$A:$B,2,FALSE) -> Others | G81: Pet Insurance | H81: 45145 | I81: 45510 | J81: 165600 | K81: =J81*0.18 -> 29808 | L81: =J81+K81 -> 195408 | M81: =L81*0.05 -> 9770.4 | N81: Retail | O81: Renew | P81: =IF(COUNTIF(B:B,B81)=1,"New Client","Old Client") -> New Client | Q81: =IF(COUNTIFS($B:$B,$B81,$F:$F,"Liability")>0,"Yes","No") -> No | R81: =IF(AND($Q81="Yes",$F81<>"Liability"),"Cross-Sold","")
A82: PL 600 | B82: 188 | C82: Offline | D82: Not POS | E82: United India Insurance Co Ltd | F82: =VLOOKUP(G82,'Policy Type'!$A:$B,2,FALSE) -> Others | G82: Individual Health | H82: 45151 | I82: 45516 | J82: 1413300 | K82: =J82*0.18 -> 254394 | L82: =J82+K82 -> 1667694 | M82: =L82*0.15 -> 250154.1 | N82: Retail | O82: Renew | P82: =IF(COUNTIF(B:B,B82)=1,"New Client","Old Client") -> Old Client | Q82: =IF(COUNTIFS($B:$B,$B82,$F:$F,"Liability")>0,"Yes","No") -> Yes | R82: =IF(AND($Q82="Yes",$F82<>"Liability"),"Cross-Sold","") -> Cross-Sold
A83: PL 601 | B83: 236 | C83: Ads | D83: Not POS | E83: Bajaj Allianz General Insurance Co Ltd | F83: =VLOOKUP(G83,'Policy Type'!$A:$B,2,FALSE) -> P&C | G83: Private Car | H83: 45169 | I83: 45534 | J83: 477428 | K83: =J83*0.18 -> 85937.04 | L83: =J83+K83 -> 563365.04 | M83: =L83*0.2 -> 112673.01 | N83: Retail | O83: Renew | P83: =IF(COUNTIF(B:B,B83)=1,"New Client","Old Client") -> New Client | Q83: =IF(COUNTIFS($B:$B,$B83,$F:$F,"Liability")>0,"Yes","No") -> No | R83: =IF(AND($Q83="Yes",$F83<>"Liability"),"Cross-Sold","")
A84: PL 602 | B84: 144 | C84: BD | D84: Not POS | E84: United India Insurance Co Ltd | F84: =VLOOKUP(G84,'Policy Type'!$A:$B,2,FALSE) -> P&C | G84: Private Car | H84: 45169 | I84: 45534 | J84: 912140 | K84: =J84*0.18 -> 164185.2 | L84: =J84+K84 -> 1076325.2 | M84: =L84*0.2 -> 215265.04 | N84: Retail | O84: Renew | P84: =IF(COUNTIF(B:B,B84)=1,"New Client","Old Client") -> Old Client | Q84: =IF(COUNTIFS($B:$B,$B84,$F:$F,"Liability")>0,"Yes","No") -> No | R84: =IF(AND($Q84="Yes",$F84<>"Liability"),"Cross-Sold","")
A85: PL 603 | B85: 51 | C85: BD | D85: Not POS | E85: Future Generali India Insurance Co Ltd | F85: =VLOOKUP(G85,'Policy Type'!$A:$B,2,FALSE) -> Others | G85: Private car - OD | H85: 45163 | I85: 45528 | J85: 2116300 | K85: =J85*0.18 -> 380934 | L85: =J85+K85 -> 2497234 | M85: =L85*0.15 -> 374585.1 | N85: Retail | O85: Renew | P85: =IF(COUNTIF(B:B,B85)=1,"New Client","Old Client") -> Old Client | Q85: =IF(COUNTIFS($B:$B,$B85,$F:$F,"Liability")>0,"Yes","No") -> No | R85: =IF(AND($Q85="Yes",$F85<>"Liability"),"Cross-Sold","")
A86: PL 604 | B86: 237 | C86: Ads | D86: Not POS | E86: United India Insurance Co Ltd | F86: =VLOOKUP(G86,'Policy Type'!$A:$B,2,FALSE) -> P&C | G86: Two wheeler - TP | H86: 45160 | I86: 45525 | J86: 117600 | K86: =J86*0.18 -> 21168 | L86: =J86+K86 -> 138768 | M86: =L86*0.2 -> 27753.6 | N86: Retail | O86: Renew | P86: =IF(COUNTIF(B:B,B86)=1,"New Client","Old Client") -> New Client | Q86: =IF(COUNTIFS($B:$B,$B86,$F:$F,"Liability")>0,"Yes","No") -> No | R86: =IF(AND($Q86="Yes",$F86<>"Liability"),"Cross-Sold","")
A87: PL 605 | B87: 238 | C87: BD | D87: Not POS | E87: Bajaj Allianz General Insurance Co Ltd | F87: =VLOOKUP(G87,'Policy Type'!$A:$B,2,FALSE) -> P&C | G87: Two Wheeler | H87: 45147 | I87: 45512 | J87: 141482 | K87: =J87*0.18 -> 25466.76 | L87: =J87+K87 -> 166948.76 | M87: =L87*0.2 -> 33389.752 | N87: Retail | O87: Renew | P87: =IF(COUNTIF(B:B,B87)=1,"New Client","Old Client") -> Old Client | Q87: =IF(COUNTIFS($B:$B,$B87,$F:$F,"Liability")>0,"Yes","No") -> Yes | R87: =IF(AND($Q87="Yes",$F87<>"Liability"),"Cross-Sold","") -> Cross-Sold
A88: PL 606 | B88: 239 | C88: Offline | D88: Not POS | E88: United India Insurance Co Ltd | F88: =VLOOKUP(G88,'Policy Type'!$A:$B,2,FALSE) -> Others | G88: Individual Health | H88: 45163 | I88: 45528 | J88: 2485600 | K88: =J88*0.18 -> 447408 | L88: =J88+K88 -> 2933008 | M88: =L88*0.15 -> 439951.2 | N88: Retail | O88: Renew | P88: =IF(COUNTIF(B:B,B88)=1,"New Client","Old Client") -> Old Client | Q88: =IF(COUNTIFS($B:$B,$B88,$F:$F,"Liability")>0,"Yes","No") -> No | R88: =IF(AND($Q88="Yes",$F88<>"Liability"),"Cross-Sold","")
A89: PL 607 | B89: 239 | C89: BD | D89: Not POS | E89: United India Insurance Co Ltd | F89: =VLOOKUP(G89,'Policy Type'!$A:$B,2,FALSE) -> Others | G89: Individual Health | H89: 45163 | I89: 45528 | J89: 2869300 | K89: =J89*0.18 -> 516474 | L89: =J89+K89 -> 3385774 | M89: =L89*0.15 -> 507866.1 | N89: Retail | O89: Renew | P89: =IF(COUNTIF(B:B,B89)=1,"New Client","Old Client") -> Old Client | Q89: =IF(COUNTIFS($B:$B,$B89,$F:$F,"Liability")>0,"Yes","No") -> No | R89: =IF(AND($Q89="Yes",$F89<>"Liability"),"Cross-Sold","")
A90: PL 608 | B90: 240 | C90: BD | D90: Not POS | E90: United India Insurance Co Ltd | F90: =VLOOKUP(G90,'Policy Type'!$A:$B,2,FALSE) -> Others | G90: Individual Health | H90: 45166 | I90: 45531 | J90: 4457900 | K90: =J90*0.18 -> 802422 | L90: =J90+K90 -> 5260322 | M90: =L90*0.15 -> 789048.3 | N90: Retail | O90: Renew | P90: =IF(COUNTIF(B:B,B90)=1,"New Client","Old Client") -> New Client | Q90: =IF(COUNTIFS($B:$B,$B90,$F:$F,"Liability")>0,"Yes","No") -> No | R90: =IF(AND($Q90="Yes",$F90<>"Liability"),"Cross-Sold","")
A91: PL 609 | B91: 241 | C91: Offline | D91: Not POS | E91: Bajaj Allianz General Insurance Co Ltd | F91: =VLOOKUP(G91,'Policy Type'!$A:$B,2,FALSE) -> Others | G91: Pet Insurance | H91: 45155 | I91: 45520 | J91: 157400 | K91: =J91*0.18 -> 28332 | L91: =J91+K91 -> 185732 | M91: =L91*0.15 -> 27859.8 | N91: Retail | O91: Renew | P91: =IF(COUNTIF(B:B,B91)=1,"New Client","Old Client") -> New Client | Q91: =IF(COUNTIFS($B:$B,$B91,$F:$F,"Liability")>0,"Yes","No") -> No | R91: =IF(AND($Q91="Yes",$F91<>"Liability"),"Cross-Sold","")
A92: PL 610 | B92: 242 | C92: BD | D92: Not POS | E92: Bajaj Allianz General Insurance Co Ltd | F92: =VLOOKUP(G92,'Policy Type'!$A:$B,2,FALSE) -> Others | G92: Pet Insurance | H92: 45161 | I92: 45526 | J92: 715100 | K92: =J92*0.18 -> 128718 | L92: =J92+K92 -> 843818 | M92: =L92*0.15 -> 126572.7 | N92: Retail | O92: Renew | P92: =IF(COUNTIF(B:B,B92)=1,"New Client","Old Client") -> New Client | Q92: =IF(COUNTIFS($B:$B,$B92,$F:$F,"Liability")>0,"Yes","No") -> No | R92: =IF(AND($Q92="Yes",$F92<>"Liability"),"Cross-Sold","")
A93: PL 611 | B93: 148 | C93: BD | D93: Not POS | E93: Bajaj Allianz General Insurance Co Ltd | F93: =VLOOKUP(G93,'Policy Type'!$A:$B,2,FALSE) -> Liability | G93: D & O | H93: 45157 | I93: 45522 | J93: 3000000 | K93: =J93*0.18 -> 540000 | L93: =J93+K93 -> 3540000 | M93: =L93*0.2 -> 708000 | N93: Corporate | O93: Renew | P93: =IF(COUNTIF(B:B,B93)=1,"New Client","Old Client") -> Old Client | Q93: =IF(COUNTIFS($B:$B,$B93,$F:$F,"Liability")>0,"Yes","No") -> Yes | R93: =IF(AND($Q93="Yes",$F93<>"Liability"),"Cross-Sold","")
A94: PL 612 | B94: 243 | C94: Offline | D94: Not POS | E94: Bajaj Allianz General Insurance Co Ltd | F94: =VLOOKUP(G94,'Policy Type'!$A:$B,2,FALSE) -> Others | G94: Pet Insurance | H94: 45156 | I94: 45521 | J94: 65100 | K94: =J94*0.18 -> 11718 | L94: =J94+K94 -> 76818 | M94: =L94*0.15 -> 11522.7 | N94: Retail | O94: Renew | P94: =IF(COUNTIF(B:B,B94)=1,"New Client","Old Client") -> New Client | Q94: =IF(COUNTIFS($B:$B,$B94,$F:$F,"Liability")>0,"Yes","No") -> No | R94: =IF(AND($Q94="Yes",$F94<>"Liability"),"Cross-Sold","")
A95: PL 613 | B95: 244 | C95: Offline | D95: Not POS | E95: TATA AIG General Insurance Co Ltd | F95: =VLOOKUP(G95,'Policy Type'!$A:$B,2,FALSE) -> Others | G95: Group Mediclaim | H95: 45147 | I95: 45512 | J95: 27711200 | K95: =J95*0.18 -> 4988016 | L95: =J95+K95 -> 32699216 | M95: =L95*0.15 -> 4904882.4 | N95: Retail | O95: Renew | P95: =IF(COUNTIF(B:B,B95)=1,"New Client","Old Client") -> Old Client | Q95: =IF(COUNTIFS($B:$B,$B95,$F:$F,"Liability")>0,"Yes","No") -> Yes | R95: =IF(AND($Q95="Yes",$F95<>"Liability"),"Cross-Sold","") -> Cross-Sold
A96: PL 614 | B96: 66 | C96: POS | D96: Indore | E96: Bajaj Allianz General Insurance Co Ltd | F96: =VLOOKUP(G96,'Policy Type'!$A:$B,2,FALSE) -> Others | G96: Group Mediclaim | H96: 45154 | I96: 45519 | J96: 13777300 | K96: =J96*0.18 -> 2479914 | L96: =J96+K96 -> 16257214 | M96: =L96*0.05 -> 812860.7 | N96: Corporate | O96: Renew | P96: =IF(COUNTIF(B:B,B96)=1,"New Client","Old Client") -> Old Client | Q96: =IF(COUNTIFS($B:$B,$B96,$F:$F,"Liability")>0,"Yes","No") -> Yes | R96: =IF(AND($Q96="Yes",$F96<>"Liability"),"Cross-Sold","") -> Cross-Sold
A97: PL 615 | B97: 245 | C97: Ads | D97: Not POS | E97: Bajaj Allianz General Insurance Co Ltd | F97: =VLOOKUP(G97,'Policy Type'!$A:$B,2,FALSE) -> Others | G97: Pet Insurance | H97: 45147 | I97: 45512 | J97: 398800 | K97: =J97*0.18 -> 71784 | L97: =J97+K97 -> 470584 | M97: =L97*0.15 -> 70587.6 | N97: Retail | O97: Renew | P97: =IF(COUNTIF(B:B,B97)=1,"New Client","Old Client") -> New Client | Q97: =IF(COUNTIFS($B:$B,$B97,$F:$F,"Liability")>0,"Yes","No") -> No | R97: =IF(AND($Q97="Yes",$F97<>"Liability"),"Cross-Sold","")
A98: PL 618 | B98: 246 | C98: POS | D98: Nagpur | E98: Future Generali India Insurance Co Ltd | F98: =VLOOKUP(G98,'Policy Type'!$A:$B,2,FALSE) -> Others | G98: Health Suraksha | H98: 45158 | I98: 45523 | J98: 3152800 | K98: =J98*0.18 -> 567504 | L98: =J98+K98 -> 3720304 | M98: =L98*0.05 -> 186015.2 | N98: Retail | O98: Renew | P98: =IF(COUNTIF(B:B,B98)=1,"New Client","Old Client") -> New Client | Q98: =IF(COUNTIFS($B:$B,$B98,$F:$F,"Liability")>0,"Yes","No") -> No | R98: =IF(AND($Q98="Yes",$F98<>"Liability"),"Cross-Sold","")
A99: PL 619 | B99: 247 | C99: POS | D99: Mumbai | E99: Bajaj Allianz General Insurance Co Ltd | F99: =VLOOKUP(G99,'Policy Type'!$A:$B,2,FALSE) -> Others | G99: Health Guard | H99: 45159 | I99: 45524 | J99: 3294600 | K99: =J99*0.18 -> 593028 | L99: =J99+K99 -> 3887628 | M99: =L99*0.05 -> 194381.4 | N99: Retail | O99: Renew | P99: =IF(COUNTIF(B:B,B99)=1,"New Client","Old Client") -> Old Client | Q99: =IF(COUNTIFS($B:$B,$B99,$F:$F,"Liability")>0,"Yes","No") -> No | R99: =IF(AND($Q99="Yes",$F99<>"Liability"),"Cross-Sold","")
A100: PL 620 | B100: 247 | C100: POS | D100: Mumbai | E100: Bajaj Allianz General Insurance Co Ltd | F100: =VLOOKUP(G100,'Policy Type'!$A:$B,2,FALSE) -> Others | G100: Global Personal Guard | H100: 45160 | I100: 45525 | J100: 1047700 | K100: =J100*0.18 -> 188586 | L100: =J100+K100 -> 1236286 | M100: =L100*0.05 -> 61814.3 | N100: Retail | O100: Renew | P100: =IF(COUNTIF(B:B,B100)=1,"New Client","Old Client") -> Old Client | Q100: =IF(COUNTIFS($B:$B,$B100,$F:$F,"Liability")>0,"Yes","No") -> No | R100: =IF(AND($Q100="Yes",$F100<>"Liability"),"Cross-Sold","")
...

Sheet Pivot Table 6
A1: SUM of Gross Premium | B1: Client Type
A2: Policy Name | B2: Corporate | C2: Retail | D2: (blank) | E2: Grand Total
A3: All Business Risk | B3: 5397100 | E3: 5397100
A4: Arogya Sanjeevani | C4: 4626700 | E4: 4626700
A5: Bharat Griha Raksha | C5: 952100 | E5: 952100
A6: Bharat Laghu Udyam Suraksha | B6: 140048100 | E6: 140048100
A7: Bharat Sookshma Udyam Suraksha | B7: 34109100 | C7: 9431400 | E7: 43540500
A8: Burglary | B8: 86099000 | C8: 704800 | E8: 86803800
A9: Business Suraksha | B9: 45800200 | C9: 1016900 | E9: 46817100
A10: Commercial Crime | B10: 159654000 | E10: 159654000
A11: Commercial General Liability | B11: 493984100 | E11: 493984100
A12: Commercial Package | B12: 128604000 | C12: 10079000 | E12: 138683000
A13: Compact insurance | B13: 982900 | E13: 982900
A14: Contractor All Risk | B14: 639839900 | C14: 13518900 | E14: 653358800
A15: Contractor's Plant and Machinery | B15: 26437700 | C15: 1149400 | E15: 27587100
A16: Cyber Crime | B16: 1191574400 | E16: 1191574400
A17: D & O | B17: 455232100 | E17: 455232100
A18: Directors and Officers | B18: 181465800 | E18: 181465800
A19: E & O | B19: 422704400 | C19: 26194500 | E19: 448898900
A20: Electronic Equipment Policy | B20: 81697800 | E20: 81697800
A21: Erection All Risk | B21: 244211700 | E21: 244211700
A22: Errors and Omisssions | B22: 327098500 | C22: 531100 | E22: 327629600
A23: Extra Care | C23: 16907000 | E23: 16907000
A24: Extra Care Plus | B24: 594900 | C24: 19082200 | E24: 19677100
A25: Family Medicare | C25: 86654700 | E25: 86654700
A26: Fidelity Guarantee | C26: 35400 | E26: 35400
A27: FinTech Policy | B27: 80240000 | E27: 80240000
A28: Global Personal Guard | C28: 26050300 | E28: 26050300
A29: Goods Carrying Commercial Vehicle | B29: 136750700 | C29: 190543800 | E29: 327294500
A30: Goods Carrying Commercial Vehicle - TP | B30: 25430400 | C30: 23760700 | E30: 49191100
A31: Group Mediclaim | B31: 3857246600 | C31: 27711200 | E31: 3884957800
A32: Group Personal Accident | B32: 328225900 | E32: 328225900
A33: Happy Family Floater | C33: 17335900 | E33: 17335900
A34: Health Absolute | B34: 2046300 | C34: 34306700 | E34: 36353000
A35: Health Guard | C35: 149209900 | E35: 149209900
A36: Health Supreme | C36: 30960700 | E36: 30960700
A37: Health Suraksha | B37: 863500 | C37: 119878800 | E37: 120742300
A38: Health Total | C38: 19653400 | E38: 19653400
A39: Home Insurance | B39: 4283300 | C39: 53373300 | E39: 57656600
A40: Hospital Cash | C40: 383500 | E40: 383500
A41: Householder Package | B41: 155800 | C41: 2137500 | E41: 2293300
A42: Individual Health | B42: 3950000 | C42: 427813100 | E42: 431763100
A43: Individual Mediclaim | C43: 890700 | E43: 890700
A44: Industrial All Risk | B44: 85205100 | E44: 85205100
A45: Machinery Breakdown | B45: 299673700 | E45: 299673700
A46: Marine Open | B46: 403592100 | C46: 1770100 | E46: 405362200
A47: Marine STOP | B47: 247826700 | E47: 247826700
A48: Medicare | C48: 50735500 | E48: 50735500
A49: Medicare Premier | C49: 68123900 | E49: 68123900
A50: Miscellaneous Vehicle | B50: 24870800 | C50: 5487900 | E50: 30358700
A51: Money | B51: 7821400 | E51: 7821400
A52: Multimedia Liability | B52: 31340800 | E52: 31340800
A53: Office Package | B53: 97515100 | C53: 1018000 | E53: 98533100
A54: Optima Secure | C54: 10570700 | E54: 10570700
A55: Package Policy | B55: 80685100 | C55: 149700 | E55: 80834800
A56: Passenger Carrying Vehicle | B56: 17873000 | C56: 6802600 | E56: 24675600
A57: Personal Accident | B57: 39100 | C57: 13113200 | E57: 13152300
A58: Pet Insurance | C58: 20867400 | E58: 20867400
A59: Premium Personal Guard | B59: 646100 | C59: 11215800 | E59: 11861900
A60: Private Car | B60: 359665269 | C60: 220775430 | E60: 580440699
A61: Private car - OD | B61: 182447900 | C61: 96333800 | E61: 278781700
A62: Private Car - TP | B62: 2536200 | C62: 9133300 | E62: 11669500
A63: Product Liability | B63: 157353000 | E63: 157353000
A64: Professional Indemnity | B64: 576674800 | C64: 21603600 | E64: 598278400
A65: Public Liability | B65: 106435760 | C65: 2382818 | E65: 108818578
A66: Shopkeeper | B66: 27583700 | C66: 2245200 | E66: 29828900
A67: Special Contingency | B67: 53100000 | E67: 53100000
A68: Specific Marine | B68: 60693400 | C68: 3008900 | E68: 63702300
A69: Standard Fire and Special perils | B69: 2898317500 | C69: 88936000 | E69: 2987253500
A70: Star Package | C70: 68800100 | E70: 68800100
A71: Top Up | B71: 28361300 | C71: 23844400 | E71: 52205700
A72: Travel | B72: 1112000 | C72: 35145400 | E72: 36257400
A73: Two Wheeler | B73: 6275120 | C73: 36717562 | E73: 42992682
A74: Two Wheeler - OD | B74: 1252100 | C74: 2761100 | E74: 4013200
A75: Two wheeler - TP | B75: 705200 | C75: 1950900 | E75: 2656100
A76: Workmen Compensation | B76: 519334400 | C76: 13124900 | E76: 532459300
A77: (blank)
A78: Grand Total | B78: 15383664849 | C78: 2131511810 | E78: 17515176659

Sheet Pivot Table 5
A1: POS Location | B1: SUM of Gross Premium
A2: Ahemdabad | B2: 820599782
A3: Indore | B3: 956218884
A4: Mumbai | B4: 1386657356
A5: Nagpur | B5: 740109090
A6: Not POS | B6: 13611591547
A7: (blank)
A8: Grand Total | B8: 17515176659

Sheet Pivot Table 4
A1: Policy MIS New | B1: SUM of Gross Premium
A2: Endorsement
A3: New | B3: 6179396439
A4: Renew | B4: 8538863038
A5: Rollover | B5: 2796917182
A6: Grand Total | B6: 17515176659

Sheet Pivot Table 3
A1: Client Type | B1: SUM of Gross Premium
A2: Corporate | B2: 15383664849
A3: Retail | B3: 2131511810
A4: (blank)
A5: Grand Total | B5: 17515176659

Sheet Pivot Table 2
A1: Insurer Name | B1: SUM of Gross Premium
A2: Aditya Birla Insurance Company | B2: 137648500
A3: Bajaj Allianz General Insurance Co Ltd | B3: 2175950094
A4: Care Health Ltd | B4: 373367100
A5: Cholamandalam MS General Insurance | B5: 197695200 | D5: =MAX(B3:B25) -> 0
A6: Future Generali India Insurance Co Ltd | B6: 1585461428
A7: Go Digit General Insurance Ltd | B7: 266294721
A8: HDFC Ergo General Insurance Co Ltd | B8: 3640304492
A9: ICICI Lombard General Insurance Co Ltd | B9: 1310493904
A10: Iffco tokio general insurance co ltd | B10: 203466212
A11: Kotak Mahindra General Insurance Co. Ltd. | B11: 21577890
A12: Liberty General Insurance | B12: 726169876
A13: Magma HDI General Insurance Co Ltd | B13: 51366000
A14: National Insurance Co Ltd | B14: 446985100
A15: New India Assurance company | B15: 1174382436
A16: Niva Bupa Health Insurance Company Ltd | B16: 61029800
A17: Raheja QBE General Insurance Co. Ltd. | B17: 4081600
... A24: United India Insurance Co Ltd | B24: 1328011660
A25: (blank)
D29: =IFERROR(__xludf.DUMMYFUNCTION("QUERY(A:B, ""select A, sum(B) group by A order by sum(B) desc limit 5"", 1)"),"Insurer Name") -> Insurer Name | E29: =IFERROR(__xludf.DUMMYFUNCTION("""COMPUTED_VALUE"""),"sum SUM of Gross Premium") -> sum SUM of Gross Premium
D30: =IFERROR(__xludf.DUMMYFUNCTION("""COMPUTED_VALUE"""),"HDFC Ergo General Insurance Co Ltd") -> HDFC Ergo General Insurance Co Ltd | E30: =IFERROR(__xludf.DUMMYFUNCTION("""COMPUTED_VALUE"""),3640304492) -> 3640304492
D31: =IFERROR(__xludf.DUMMYFUNCTION("""COMPUTED_VALUE"""),"Bajaj Allianz General Insurance Co Ltd") -> Bajaj Allianz General Insurance Co Ltd | E31: =IFERROR(__xludf.DUMMYFUNCTION("""COMPUTED_VALUE"""),2175950094) -> 2175950094
D32: =IFERROR(__xludf.DUMMYFUNCTION("""COMPUTED_VALUE"""),"Future Generali India Insurance Co Ltd") -> Future Generali India Insurance Co Ltd | E32: =IFERROR(__xludf.DUMMYFUNCTION("""COMPUTED_VALUE"""),1585461428) -> 1585461428
D33: =IFERROR(__xludf.DUMMYFUNCTION("""COMPUTED_VALUE"""),"United India Insurance Co Ltd") -> United India Insurance Co Ltd | E33: =IFERROR(__xludf.DUMMYFUNCTION("""COMPUTED_VALUE"""),1328011660) -> 1328011660
D34: =IFERROR(__xludf.DUMMYFUNCTION("""COMPUTED_VALUE"""),"ICICI Lombard General Insurance Co Ltd") -> ICICI Lombard General Insurance Co Ltd | E34: =IFERROR(__xludf.DUMMYFUNCTION("""COMPUTED_VALUE"""),1310493904) -> 1310493904

Sheet Appendix>>

Sheet Policy Type
A1: Policy | B1: Category
A2: Workmen Compensation | B2: Liability
A3: Burglary | B3: P&C
A4: Marine Open | B4: P&C
A5: Premium Personal Guard | B5: P&C
A6: Two Wheeler | B6: P&C
A7: D & O | B7: Liability
A8: Two wheeler - TP | B8: P&C
A9: Private Car | B9: P&C
A10: Two Wheeler - OD | B10: P&C
A11: Specific Marine | B11: P&C
A12: E & O | B12: Liability
... A75: Arogya Sanjeevani | B75: Liability

Sheet Dashboards
A1: POS Dashboard - BIMA KAVACH
A2: Sales Channel | B2: SUM of Gross Premium | C2: SUM of Gross Premium
A3: Ads | B3: 5067132494 | C3: 17515176659
A4: BD | B4: 4260590787
A5: Offline | B5: 4283868266
A6: POS | B6: 3903585112
A7: (blank)
A8: Grand Total | B8: 17515176659

Sheet Crossssss
A1: Policy Name | B1: GWP
A2: Burglary | B2: =SUMIFS('Raw Data'!$J:$J,'Raw Data'!$G:$G,A2,'Raw Data'!$R:$R,"Cross-Sold") -> 42770500
A3: Marine Open | B3: =SUMIFS('Raw Data'!$J:$J,'Raw Data'!$G:$G,A3,'Raw Data'!$R:$R,"Cross-Sold") -> 174568900 | D3: =MAX(B2:B4143) -> 1184589200
A4: D & O | B4: =SUMIFS('Raw Data'!$J:$J,'Raw Data'!$G:$G,A4,'Raw Data'!$R:$R,"Cross-Sold") -> 0
A5: Two Wheeler | B5: =SUMIFS('Raw Data'!$J:$J,'Raw Data'!$G:$G,A5,'Raw Data'!$R:$R,"Cross-Sold") -> 13740226 | D5: {=INDEX(A2:A100,MATCH(MAX(B2:B100),B2:B100,0))} -> Group Mediclaim
A6: Two Wheeler | B6: =SUMIFS('Raw Data'!$J:$J,'Raw Data'!$G:$G,A6,'Raw Data'!$R:$R,"Cross-Sold") -> 13740226
A7: Two Wheeler | B7: =SUMIFS('Raw Data'!$J:$J,'Raw Data'!$G:$G,A7,'Raw Data'!$R:$R,"Cross-Sold") -> 13740226
A8: Marine Open | B8: =SUMIFS('Raw Data'!$J:$J,'Raw Data'!$G:$G,A8,'Raw Data'!$R:$R,"Cross-Sold") -> 174568900
A9: Specific Marine | B9: =SUMIFS('Raw Data'!$J:$J,'Raw Data'!$G:$G,A9,'Raw Data'!$R:$R,"Cross-Sold") -> 29707200
A10: D & O | B10: =SUMIFS('Raw Data'!$J:$J,'Raw Data'!$G:$G,A10,'Raw Data'!$R:$R,"Cross-Sold") -> 0
A11: E & O | B11: =SUMIFS('Raw Data'!$J:$J,'Raw Data'!$G:$G,A11,'Raw Data'!$R:$R,"Cross-Sold") -> 0
A12: Star Package | B12: =SUMIFS('Raw Data'!$J:$J,'Raw Data'!$G:$G,A12,'Raw Data'!$R:$R,"Cross-Sold") -> 26771200
A13: Shopkeeper | B13: =SUMIFS('Raw Data'!$J:$J,'Raw Data'!$G:$G,A13,'Raw Data'!$R:$R,"Cross-Sold") -> 7391100
A14: Public Liability | B14: =SUMIFS('Raw Data'!$J:$J,'Raw Data'!$G:$G,A14,'Raw Data'!$R:$R,"Cross-Sold") -> 0
A15: Workmen Compensation | B15: =SUMIFS('Raw Data'!$J:$J,'Raw Data'!$G:$G,A15,'Raw Data'!$R:$R,"Cross-Sold") -> 0
A16: Bharat Sookshma Udyam Suraksha | B16: =SUMIFS('Raw Data'!$J:$J,'Raw Data'!$G:$G,A16,'Raw Data'!$R:$R,"Cross-Sold") -> 15227800
A17: D & O | B17: =SUMIFS('Raw Data'!$J:$J,'Raw Data'!$G:$G,A17,'Raw Data'!$R:$R,"Cross-Sold") -> 0
... A4143: Errors and Omisssions | B4143: =SUMIFS('Raw Data'!$J:$J,'Raw Data'!$G:$G,A4143,'Raw Data'!$R:$R,"Cross-Sold") -> 0
